odoo/addons/res_company_code/README.rst
odoo/addons/res_company_code/__init__.py
odoo/addons/res_company_code/__manifest__.py
odoo/addons/res_company_code/demo/res_company.xml
odoo/addons/res_company_code/demo/res_groups.xml
odoo/addons/res_company_code/i18n/es.po
odoo/addons/res_company_code/i18n/fr.po
odoo/addons/res_company_code/i18n/it.po
odoo/addons/res_company_code/i18n/res_company_code.pot
odoo/addons/res_company_code/models/__init__.py
odoo/addons/res_company_code/models/ir_http.py
odoo/addons/res_company_code/models/res_company.py
odoo/addons/res_company_code/readme/CONTRIBUTORS.md
odoo/addons/res_company_code/readme/DESCRIPTION.md
odoo/addons/res_company_code/static/description/icon.png
odoo/addons/res_company_code/static/description/index.html
odoo/addons/res_company_code/static/description/res_company_form.png
odoo/addons/res_company_code/static/description/res_company_tree.png
odoo/addons/res_company_code/static/description/switch_company_menu.png
odoo/addons/res_company_code/tests/__init__.py
odoo/addons/res_company_code/tests/test_res_company_code.py
odoo/addons/res_company_code/views/view_res_company.xml
odoo_addon_res_company_code-18.0.1.0.1.dist-info/METADATA
odoo_addon_res_company_code-18.0.1.0.1.dist-info/WHEEL
odoo_addon_res_company_code-18.0.1.0.1.dist-info/top_level.txt
odoo_addon_res_company_code-18.0.1.0.1.dist-info/RECORD
