Metadata-Version: 2.1
Name: odoo-addon-res_company_code
Version: 18.0.1.0.1
Requires-Python: >=3.10
Requires-Dist: odoo-addon-res_company_search_view==18.0.*
Requires-Dist: odoo==18.0.*
Summary: Add 'code' field on company model
Home-page: https://github.com/OCA/multi-company
License: AGPL-3
Author: GRAP, Odoo Community Association (OCA)
Author-email: support@odoo-community.org
Classifier: Programming Language :: Python
Classifier: Framework :: Odoo
Classifier: Framework :: Odoo :: 18.0
Classifier: License :: OSI Approved :: GNU Affero General Public License v3
